metarknn/__init__.py
metarknn/app/__init__.py
metarknn/app/classification.py
metarknn/app/detection.py
metarknn/app/face_detection.py
metarknn/app/face_embedding.py
metarknn/app/face_recognition.py
metarknn/app/obb_detection.py
metarknn/app/person_detection.py
metarknn/app/quantization.py
metarknn/app/segment.py
metarknn/model_zoo/__init__.py
metarknn/model_zoo/model.py
metarknn/utils/__init__.py
metarknn/utils/general.py
meta_rknn-0.1.2.dist-info/METADATA
meta_rknn-0.1.2.dist-info/WHEEL
meta_rknn-0.1.2.dist-info/top_level.txt
meta_rknn-0.1.2.dist-info/zip-safe
meta_rknn-0.1.2.dist-info/RECORD
